hexmq/__init__.py
hexmq/comsumer.py
hexmq/encode.py
hexmq/mq_type.py
hexmq/producer.py
hexmq/adapters/__init__.py
hexmq/adapters/comsumer_rocketmq.py
hexmq/adapters/mq_factory.py
hexmq/adapters/producer_rocketmq.py
xmq-python/__init__.py
xmq-python/comsumer.py
xmq-python/encode.py
xmq-python/mq_type.py
xmq-python/producer.py
xmq-python/adapters/__init__.py
xmq-python/adapters/comsumer_rocketmq.py
xmq-python/adapters/mq_factory.py
xmq-python/adapters/producer_rocketmq.py
xmq_python/__init__.py
xmq_python/comsumer.py
xmq_python/consumer.py
xmq_python/encode.py
xmq_python/mq_type.py
xmq_python/producer.py
xmq_python/adapters/__init__.py
xmq_python/adapters/comsumer_amqp.py
xmq_python/adapters/comsumer_rocketmq.py
xmq_python/adapters/consumer_amqp.py
xmq_python/adapters/consumer_rocketmq.py
xmq_python/adapters/mq_factory.py
xmq_python/adapters/producer_amqp.py
xmq_python/adapters/producer_rocketmq.py
xmq_python/utils/AliyunCredentialsProvider3.py
xmq_python/utils/__init__.py
xmq_python-0.0.13.dist-info/LICENSE
xmq_python-0.0.13.dist-info/METADATA
xmq_python-0.0.13.dist-info/WHEEL
xmq_python-0.0.13.dist-info/top_level.txt
xmq_python-0.0.13.dist-info/RECORD
