Metadata-Version: 2.1
Name: xmq-python
Version: 0.0.13
Summary: mq的python封装包
Home-page: UNKNOWN
Author: neil
Author-email: 
License: UNKNOWN
Platform: UNKNOWN
Classifier: Programming Language :: Python :: 3
Classifier: License :: OSI Approved :: MIT License
Classifier: Operating System :: OS Independent
Requires-Python: >=3.6
Requires-Dist: rocketmq-client-python (==2.0.0)
Requires-Dist: pika (==1.2.0)
